<?xml version="1.0" encoding="UTF-8" ?>
<page-map xmlns="http://www.idpf.org/2007/opf">
  <page name="1" href="cover.xhtml" />
  <page name="2" href="copyright-page.xhtml" />
  <page name="3" href="biography.xhtml" />
  <page name="4" href="titlepage.xhtml" />
  <page name="5" href="dedication.xhtml" />
  <page name="6" href="introduction.xhtml" />
  <page name="7" href="introduction.xhtml#GBS.0007.05" />
  <page name="8" href="introduction.xhtml#GBS.0008.04" />
  <page name="9" href="introduction.xhtml#GBS.0009.01" />
  <page name="10" href="introduction.xhtml#GBS.0010.01" />
  <page name="11" href="introduction.xhtml#GBS.0010.02" />
  <page name="12" href="chapter1.xhtml" />
  <page name="13" href="chapter1.xhtml#GBS.0011.05" />
  <page name="14" href="chapter1.xhtml#GBS.0012.04" />
  <page name="15" href="chapter1.xhtml#GBS.0013.03" />
  <page name="16" href="chapter1.xhtml#GBS.0014.02" />
  <page name="17" href="chapter1.xhtml#GBS.0015.01" />
  <page name="18" href="chapter2.xhtml" />
  <page name="19" href="chapter2.xhtml#GBS.0016.05" />
  <page name="20" href="chapter2.xhtml#GBS.0017.04" />
  <page name="21" href="chapter2.xhtml#GBS.0018.04" />
  <page name="22" href="chapter2.xhtml#GBS.0019.03" />
  <page name="23" href="chapter3.xhtml" />
  <page name="24" href="chapter3.xhtml#GBS.0020.05" />
  <page name="25" href="chapter3.xhtml#GBS.0021.04" />
  <page name="26" href="chapter3.xhtml#GBS.0022.03" />
  <page name="27" href="chapter3.xhtml#GBS.0023.03" />
  <page name="28" href="chapter4.xhtml" />
  <page name="29" href="chapter4.xhtml#GBS.0024.05" />
  <page name="30" href="chapter4.xhtml#GBS.0025.04" />
  <page name="31" href="chapter4.xhtml#GBS.0026.04" />
  <page name="32" href="chapter4.xhtml#GBS.0027.03" />
  <page name="33" href="chapter5.xhtml" />
  <page name="34" href="chapter5.xhtml#GBS.0028.05" />
  <page name="35" href="chapter5.xhtml#GBS.0029.04" />
  <page name="36" href="chapter5.xhtml#GBS.0030.04" />
  <page name="37" href="chapter5.xhtml#GBS.0031.04" />
  <page name="38" href="chapter6.xhtml" />
  <page name="39" href="chapter6.xhtml#GBS.0032.05" />
  <page name="40" href="chapter6.xhtml#GBS.0033.04" />
  <page name="41" href="chapter6.xhtml#GBS.0034.03" />
  <page name="42" href="chapter6.xhtml#GBS.0035.03" />
  <page name="43" href="chapter6.xhtml#GBS.0036.02" />
  <page name="44" href="chapter7.xhtml" />
  <page name="45" href="chapter7.xhtml#GBS.0037.05" />
  <page name="46" href="chapter7.xhtml#GBS.0038.04" />
  <page name="47" href="chapter7.xhtml#GBS.0039.03" />
  <page name="48" href="chapter7.xhtml#GBS.0040.02" />
  <page name="49" href="chapter8.xhtml" />
  <page name="50" href="chapter8.xhtml#GBS.0041.05" />
  <page name="51" href="chapter8.xhtml#GBS.0042.05" />
  <page name="52" href="chapter8.xhtml#GBS.0043.05" />
  <page name="53" href="chapter8.xhtml#GBS.0044.04" />
  <page name="54" href="chapter9.xhtml" />
  <page name="55" href="chapter9.xhtml#GBS.0046.05" />
  <page name="56" href="chapter9.xhtml#GBS.0047.05" />
  <page name="57" href="chapter9.xhtml#GBS.0048.04" />
  <page name="58" href="chapter10.xhtml" />
  <page name="59" href="chapter10.xhtml#GBS.0050.05" />
  <page name="60" href="chapter10.xhtml#GBS.0051.04" />
  <page name="61" href="chapter10.xhtml#GBS.0052.04" />
  <page name="62" href="chapter10.xhtml#GBS.0053.03" />
  <page name="63" href="chapter11.xhtml" />
  <page name="64" href="chapter11.xhtml#GBS.0054.05" />
  <page name="65" href="chapter11.xhtml#GBS.0055.05" />
  <page name="66" href="chapter11.xhtml#GBS.0056.04" />
  <page name="67" href="chapter11.xhtml#GBS.0057.04" />
  <page name="68" href="chapter12.xhtml" />
  <page name="69" href="chapter12.xhtml#GBS.0058.05" />
  <page name="70" href="chapter12.xhtml#GBS.0059.04" />
  <page name="71" href="chapter12.xhtml#GBS.0060.04" />
  <page name="72" href="chapter12.xhtml#GBS.0061.03" />
  <page name="73" href="chapter13.xhtml" />
  <page name="74" href="chapter13.xhtml#GBS.0062.05" />
  <page name="75" href="chapter13.xhtml#GBS.0063.04" />
  <page name="76" href="chapter13.xhtml#GBS.0064.04" />
  <page name="77" href="chapter13.xhtml#GBS.0065.03" />
  <page name="78" href="chapter14.xhtml" />
  <page name="79" href="chapter14.xhtml#GBS.0066.05" />
  <page name="80" href="chapter14.xhtml#GBS.0067.04" />
  <page name="81" href="chapter14.xhtml#GBS.0068.03" />
  <page name="82" href="chapter14.xhtml#GBS.0069.02" />
  <page name="83" href="chapter14.xhtml#GBS.0070.01" />
  <page name="84" href="chapter15.xhtml" />
  <page name="85" href="chapter15.xhtml#GBS.0071.05" />
  <page name="86" href="chapter15.xhtml#GBS.0072.04" />
  <page name="87" href="chapter15.xhtml#GBS.0073.04" />
  <page name="88" href="chapter15.xhtml#GBS.0074.03" />
  <page name="89" href="chapter16.xhtml" />
  <page name="90" href="chapter16.xhtml#GBS.0075.04" />
  <page name="91" href="chapter16.xhtml#GBS.0076.04" />
  <page name="92" href="chapter16.xhtml#GBS.0077.03" />
  <page name="93" href="chapter16.xhtml#GBS.0078.02" />
  <page name="94" href="chapter17.xhtml" />
  <page name="95" href="chapter17.xhtml#GBS.0079.05" />
  <page name="96" href="chapter17.xhtml#GBS.0080.05" />
  <page name="97" href="chapter17.xhtml#GBS.0081.04" />
  <page name="98" href="chapter17.xhtml#GBS.0082.03" />
  <page name="99" href="chapter18.xhtml" />
  <page name="100" href="chapter18.xhtml#GBS.0084.05" />
  <page name="101" href="chapter18.xhtml#GBS.0085.04" />
  <page name="102" href="chapter18.xhtml#GBS.0086.03" />
  <page name="103" href="chapter18.xhtml#GBS.0087.02" />
  <page name="104" href="chapter19.xhtml" />
  <page name="105" href="chapter19.xhtml#GBS.0088.04" />
  <page name="106" href="chapter19.xhtml#GBS.0089.04" />
  <page name="107" href="chapter19.xhtml#GBS.0090.03" />
  <page name="108" href="chapter20.xhtml" />
  <page name="109" href="chapter20.xhtml#GBS.0092.05" />
  <page name="110" href="chapter20.xhtml#GBS.0093.05" />
  <page name="111" href="chapter20.xhtml#GBS.0094.05" />
  <page name="112" href="chapter21.xhtml" />
  <page name="113" href="chapter21.xhtml#GBS.0096.05" />
  <page name="114" href="chapter21.xhtml#GBS.0097.03" />
  <page name="115" href="chapter21.xhtml#GBS.0098.03" />
  <page name="116" href="chapter21.xhtml#GBS.0099.02" />
  <page name="117" href="chapter22.xhtml" />
  <page name="118" href="chapter22.xhtml#GBS.0100.05" />
  <page name="119" href="chapter22.xhtml#GBS.0101.04" />
  <page name="120" href="chapter22.xhtml#GBS.0102.04" />
  <page name="121" href="chapter22.xhtml#GBS.0103.03" />
  <page name="122" href="chapter22.xhtml#GBS.0104.03" />
  <page name="123" href="chapter22.xhtml#GBS.0105.02" />
  <page name="124" href="chapter23.xhtml" />
  <page name="125" href="chapter23.xhtml#GBS.0106.05" />
  <page name="126" href="chapter23.xhtml#GBS.0107.04" />
  <page name="127" href="chapter23.xhtml#GBS.0108.04" />
  <page name="128" href="chapter24.xhtml" />
  <page name="129" href="chapter24.xhtml#GBS.0110.05" />
  <page name="130" href="chapter24.xhtml#GBS.0111.05" />
  <page name="131" href="chapter24.xhtml#GBS.0112.05" />
  <page name="132" href="chapter25.xhtml" />
  <page name="133" href="chapter25.xhtml#GBS.0114.05" />
  <page name="134" href="chapter25.xhtml#GBS.0115.04" />
  <page name="135" href="chapter25.xhtml#GBS.0116.03" />
  <page name="136" href="chapter25.xhtml#GBS.0117.02" />
  <page name="137" href="chapter26.xhtml" />
  <page name="138" href="chapter26.xhtml#GBS.0118.05" />
  <page name="139" href="chapter26.xhtml#GBS.0119.04" />
  <page name="140" href="chapter26.xhtml#GBS.0120.04" />
  <page name="141" href="chapter27.xhtml" />
  <page name="142" href="chapter27.xhtml#GBS.0122.05" />
  <page name="143" href="chapter27.xhtml#GBS.0123.05" />
  <page name="144" href="chapter27.xhtml#GBS.0124.05" />
  <page name="145" href="chapter27.xhtml#GBS.0125.04" />
  <page name="146" href="chapter28.xhtml" />
  <page name="147" href="chapter28.xhtml#GBS.0127.05" />
  <page name="148" href="chapter28.xhtml#GBS.0128.05" />
  <page name="149" href="chapter28.xhtml#GBS.0129.05" />
  <page name="150" href="chapter29.xhtml" />
  <page name="151" href="chapter29.xhtml#GBS.0131.05" />
  <page name="152" href="chapter29.xhtml#GBS.0132.05" />
  <page name="153" href="chapter29.xhtml#GBS.0133.05" />
  <page name="154" href="chapter30.xhtml" />
  <page name="155" href="chapter30.xhtml#GBS.0135.05" />
  <page name="156" href="chapter30.xhtml#GBS.0136.05" />
  <page name="157" href="chapter30.xhtml#GBS.0137.04" />
  <page name="158" href="chapter31.xhtml" />
  <page name="159" href="chapter31.xhtml#GBS.0139.05" />
  <page name="160" href="chapter31.xhtml#GBS.0140.05" />
  <page name="161" href="chapter31.xhtml#GBS.0141.04" />
  <page name="162" href="chapter31.xhtml#GBS.0142.04" />
  <page name="163" href="chapter31.xhtml#GBS.0143.03" />
</page-map>
